core/__init__.py
core/auto_excel.py
core/auto_mail.py
core/auto_net.py
core/auto_pdf.py
core/auto_sys.py
core/auto_web.py
pyrpasuite-0.0.2.dist-info/METADATA
pyrpasuite-0.0.2.dist-info/WHEEL
pyrpasuite-0.0.2.dist-info/top_level.txt
pyrpasuite-0.0.2.dist-info/RECORD
