Metadata-Version: 2.1
Name: pyrpasuite
Version: 0.0.2
Summary: RPA using python
Author: Muktadir
Classifier: Development Status :: 3 - Alpha
Requires-Dist: appopener ==1.7
Requires-Dist: netmiko ==4.3.0
Requires-Dist: openpyxl ==3.1.2
Requires-Dist: paramiko ==3.4.0
Requires-Dist: PyAutoGUI ==0.9.54
Requires-Dist: PyPDF2 ==3.0.1
Requires-Dist: pypdfium2 ==4.25.0
Requires-Dist: selenium ==4.16.0
Requires-Dist: urllib3 ==2.1.0
Requires-Dist: webdriver-manager ==4.0.1
